setup.py
xdiamond_jiayun/__init__.py
xdiamond_jiayun/xdiamond_jiayun.py
xdiamond_jiayun.egg-info/PKG-INFO
xdiamond_jiayun.egg-info/SOURCES.txt
xdiamond_jiayun.egg-info/dependency_links.txt
xdiamond_jiayun.egg-info/requires.txt
xdiamond_jiayun.egg-info/top_level.txt