Metadata-Version: 1.0
Name: xdiamond-jiayun
Version: 1.0.0
Summary: xdiamond_jiayun sdk
Home-page: UNKNOWN
Author: lockeCucumber
Author-email: lockeCucumber@163.com
License: MIT Licence
Keywords: pip,datacanvas,xdiamond_jiayun,lockeCucumber
Platform: any
